screenshotter/__init__.py
screenshotter/screenshotter.py
screenshotter-0.1.0.dist-info/LICENSE
screenshotter-0.1.0.dist-info/METADATA
screenshotter-0.1.0.dist-info/WHEEL
screenshotter-0.1.0.dist-info/entry_points.txt
screenshotter-0.1.0.dist-info/top_level.txt
screenshotter-0.1.0.dist-info/RECORD
