Metadata-Version: 2.1
Name: screenshotter
Version: 0.1.0
Summary: Automatically take full-screen screenshots at a fixed rate
Home-page: https://github.com/cvaugh/screenshotter
Author: Chase Vaughan
Author-email: contact@cvaugh.dev
License: MIT
Keywords: screenshot,automation
License-File: LICENSE
Requires-Dist: screeninfo (==0.8.1)
Requires-Dist: pillow (==9.3.0)
Requires-Dist: pyautogui (==0.9.53)
